telegram_click_aio/__init__.py
telegram_click_aio/argument.py
telegram_click_aio/const.py
telegram_click_aio/decorator.py
telegram_click_aio/error_handler.py
telegram_click_aio/help.py
telegram_click_aio/parser.py
telegram_click_aio/util.py
telegram_click_aio/permission/__init__.py
telegram_click_aio/permission/base.py
telegram_click_aio/permission/chat.py
telegram_click_aio/permission/user.py
telegram_click_aio-2.0.0.dist-info/LICENSE
telegram_click_aio-2.0.0.dist-info/METADATA
telegram_click_aio-2.0.0.dist-info/WHEEL
telegram_click_aio-2.0.0.dist-info/top_level.txt
telegram_click_aio-2.0.0.dist-info/RECORD
