Metadata-Version: 2.1
Name: telegram-click-aio
Version: 2.0.0
Summary: Click inspired command interface toolkit for aiogram
Home-page: https://github.com/markusressel/telegram-click-aio
Author: Markus Ressel
Author-email: mail@markusressel.de
License: MIT
Classifier: Development Status :: 5 - Production/Stable
Classifier: License :: OSI Approved :: MIT License
Classifier: Programming Language :: Python :: 3
Classifier: Programming Language :: Python :: 3.8
License-File: LICENSE
Requires-Dist: aiofiles
Requires-Dist: aiogram
Requires-Dist: aiohttp
Requires-Dist: aiosignal
Requires-Dist: annotated-types
Requires-Dist: async-timeout
Requires-Dist: attrs
Requires-Dist: certifi
Requires-Dist: charset-normalizer
Requires-Dist: emoji
Requires-Dist: frozenlist
Requires-Dist: idna
Requires-Dist: magic-filter
Requires-Dist: multidict
Requires-Dist: pydantic
Requires-Dist: pydantic-core
Requires-Dist: typing-extensions
Requires-Dist: yarl
